chinese_permanent_calendar/__init__.py
chinese_permanent_calendar/calendar_helper.py
chinese_permanent_calendar/cp_calendar.csv.gz
chinese_permanent_calendar/example.py
chinese_permanent_calendar/perpetual_calendar.py
chinese_permanent_calendar-0.1.0.dist-info/LICENSE
chinese_permanent_calendar-0.1.0.dist-info/METADATA
chinese_permanent_calendar-0.1.0.dist-info/WHEEL
chinese_permanent_calendar-0.1.0.dist-info/top_level.txt
chinese_permanent_calendar-0.1.0.dist-info/RECORD
