Metadata-Version: 2.1
Name: chinese-permanent-calendar
Version: 0.1.0
Summary: Information about Chinese perpetual calendar
Home-page: https://github.com/demeen68/chinese_permanent_calendar
Author: X.-Q.
License: MIT License
Keywords: chinese calendar,calendar
Platform: UNKNOWN
Classifier: License :: OSI Approved :: MIT License
Classifier: Programming Language :: Python :: 3
Classifier: Programming Language :: Python :: 3.5
Classifier: Programming Language :: Python :: 3.6
Classifier: Programming Language :: Python :: 3.7
Classifier: Programming Language :: Python :: 3.8
Requires-Dist: pandas
